{
  "core_event_name": "华为首款8.8英寸旗舰小平板发布",
  "comments": [
    {
      "event_title": "华为阅读眼动翻页功能新增适配 MatePad Mini、Mate X6 系列设备",
      "event_id": "event_1",
      "event_url": "http://www.ithome.com/0/881/043.htm",
      "comment_index": 0,
      "user_id": "",
      "comment_time": "",
      "comment_content": "非百家号页面，跳过评论爬取",
      "user_location": "",
      "like_count": 0,
      "scrape_time": "2025-09-12 20:33:33",
      "event_time": "9月7日 16:01"
    },
    {
      "event_title": "华为MatePad Mini亮相,超轻薄设计打造“不一样的Mini”",
      "event_id": "event_2",
      "event_url": "http://baijiahao.baidu.com/s?id=1842484523046469039&wfr=spider&for=pc",
      "comment_index": 1,
      "user_id": "小丸子不演再战江湖",
      "comment_time": "09-06 12:29",
      "comment_content": "华为这款小平板真便携，轻薄设计拿着超轻松。",
      "user_location": "安徽",
      "like_count": 0,
      "scrape_time": "2025-09-12 20:33:49",
      "event_time": "9月6日 11:42"
    },
    {
      "event_title": "华为发布首款8.8英寸旗舰小平板，以全场景能力改变市场格局",
      "event_id": "event_3",
      "event_url": "http://www.163.com/dy/article/K8MQAKN80511DP7O.html",
      "comment_index": 0,
      "user_id": "",
      "comment_time": "",
      "comment_content": "非百家号页面，跳过评论爬取",
      "user_location": "",
      "like_count": 0,
      "scrape_time": "2025-09-12 20:33:51",
      "event_time": "9月5日 13:35"
    },
    {
      "event_title": "华为全新小尺寸平板MatePad Mini发布",
      "event_id": "event_4",
      "event_url": "http://economy.southcn.com/node_cc06cbe708/5efe38e8fd.shtml",
      "comment_index": 0,
      "user_id": "",
      "comment_time": "",
      "comment_content": "非百家号页面，跳过评论爬取",
      "user_location": "",
      "like_count": 0,
      "scrape_time": "2025-09-12 20:33:53",
      "event_time": "9月4日 19:22"
    },
    {
      "event_title": "华为发布3299元8.8寸大手机!苹果没做到的 华为全做到了",
      "event_id": "event_5",
      "event_url": "http://news.pconline.com.cn/1974/19744753.html",
      "comment_index": 0,
      "user_id": "",
      "comment_time": "",
      "comment_content": "非百家号页面，跳过评论爬取",
      "user_location": "",
      "like_count": 0,
      "scrape_time": "2025-09-12 20:33:56",
      "event_time": "9月4日 17:16"
    },
    {
      "event_title": "华为发布首款8.8英寸OLED平板",
      "event_id": "event_6",
      "event_url": "http://weibo.com/3780537534/Q31iZ7naE",
      "comment_index": 0,
      "user_id": "",
      "comment_time": "",
      "comment_content": "非百家号页面，跳过评论爬取",
      "user_location": "",
      "like_count": 0,
      "scrape_time": "2025-09-12 20:33:58",
      "event_time": "9月4日 17:05"
    }
  ],
  "total_comments": 6,
  "scrape_time": "2025-09-12 20:33:58"
}