{
  "core_info": {
    "core_event_name": "哈弗大狗降价来袭",
    "update_time": "更新至20250824",
    "sub_event_count": 0,
    "scrape_time": "2025-09-11 19:24:30"
  },
  "sub_events": [
    {
      "id": "event_1",
      "title": "无锡地区哈弗大狗降价来袭!底价9.89万,错过就没有",
      "link": "http://www.autohome.com.cn/x/hq-18728119.html",
      "time": "8月24日 05:41",
      "summary": "",
      "author": ""
    },
    {
      "id": "event_2",
      "title": "哈弗大狗2026款焕新上市",
      "link": "http://www.autohome.com.cn/dealer/202508/1409049550.html",
      "time": "8月23日 10:06",
      "summary": "",
      "author": ""
    },
    {
      "id": "event_3",
      "title": "延安地区哈弗大狗降价消息",
      "link": "http://www.autohome.com.cn/x/hq-18598245.html",
      "time": "8月21日 21:30",
      "summary": "",
      "author": ""
    },
    {
      "id": "event_4",
      "title": "哈弗大狗9.89万元可提 轻越野卷王诞生",
      "link": "http://www.autohome.com.cn/dealer/202501/1305554442.html",
      "time": "1月13日 09:37",
      "summary": "",
      "author": ""
    },
    {
      "id": "event_5",
      "title": "9.89万元起限时抢购哈弗大狗开回家",
      "link": "http://www.autohome.com.cn/dealer/202501/1303638179.html",
      "time": "1月2日 15:59",
      "summary": "",
      "author": ""
    },
    {
      "id": "event_6",
      "title": "大庆哈弗二代大狗大幅降价",
      "link": "http://www.autohome.com.cn/x/hq-4796531.html",
      "time": "2024年8月4日",
      "summary": "",
      "author": ""
    },
    {
      "id": "event_7",
      "title": "哈尔滨地区哈弗大狗大幅降价!特价9.89万,赶快行动",
      "link": "http://www.autohome.com.cn/x/hq-4762810.html",
      "time": "2024年8月3日",
      "summary": "",
      "author": ""
    },
    {
      "id": "event_8",
      "title": "长沙地区哈弗大狗降价来袭!底价9.89万,仅此一次",
      "link": "http://www.autohome.com.cn/x/hq-4761855.html",
      "time": "2024年8月3日",
      "summary": "",
      "author": ""
    },
    {
      "id": "event_9",
      "title": "漳州哈弗大狗降价来袭!最高优惠2.5万",
      "link": "http://www.autohome.com.cn/x/hq-4761092.html",
      "time": "2024年8月3日",
      "summary": "",
      "author": ""
    },
    {
      "id": "event_10",
      "title": "哈弗大狗降价来袭",
      "link": "http://www.autohome.com.cn/x/hq-4759739.html",
      "time": "2024年8月3日",
      "summary": "",
      "author": ""
    },
    {
      "id": "event_11",
      "title": "海口地区哈弗大狗降价来袭,最低售价9.89万!优惠不等人",
      "link": "http://www.autohome.com.cn/x/hq-4759628.html",
      "time": "2024年8月3日",
      "summary": "",
      "author": ""
    },
    {
      "id": "event_12",
      "title": "厦门哈弗二代大狗大幅降价,底价12.98万!今日钜惠",
      "link": "http://www.autohome.com.cn/x/hq-4758687.html",
      "time": "2024年8月3日",
      "summary": "",
      "author": ""
    },
    {
      "id": "event_13",
      "title": "哈弗大狗限时抢购，9.89万起",
      "link": "http://www.autohome.com.cn/dealer/202408/1238419633.html",
      "time": "2024年8月3日",
      "summary": "",
      "author": ""
    },
    {
      "id": "event_14",
      "title": "牡丹江地区哈弗大狗大幅降价,优惠2.5万",
      "link": "http://www.autohome.com.cn/x/hq-4731687.html",
      "time": "2024年8月2日",
      "summary": "",
      "author": ""
    },
    {
      "id": "event_15",
      "title": "张家界哈弗大狗大幅降价,最新报价9.89万!限时促销",
      "link": "http://www.autohome.com.cn/x/hq-4729993.html",
      "time": "2024年8月2日",
      "summary": "",
      "author": ""
    },
    {
      "id": "event_16",
      "title": "伊犁哈弗大狗降价来袭,特价9.89万!限时促销",
      "link": "http://www.autohome.com.cn/x/hq-4714122.html",
      "time": "2024年8月2日",
      "summary": "",
      "author": ""
    },
    {
      "id": "event_17",
      "title": "双鸭山安盛9.89万元起 限时抢购哈弗大狗",
      "link": "http://www.autohome.com.cn/dealer/202408/1237660955.html",
      "time": "2024年8月1日",
      "summary": "",
      "author": ""
    },
    {
      "id": "event_18",
      "title": "乌鲁木齐地区哈弗二代大狗大幅降价",
      "link": "http://www.autohome.com.cn/x/hq-4672795.html",
      "time": "2024年7月31日",
      "summary": "",
      "author": ""
    },
    {
      "id": "event_19",
      "title": "哈弗大狗限时抢购:9.89万起!",
      "link": "http://finance.sina.com.cn/tech/roll/2024-07-30/doc-incfxeue0013256.shtml",
      "time": "2024年7月30日",
      "summary": "",
      "author": ""
    },
    {
      "id": "event_20",
      "title": "金昌哈弗大狗降价来袭!促销优惠2.5万,不容错过",
      "link": "http://www.autohome.com.cn/x/hq-4638966.html",
      "time": "2024年7月30日",
      "summary": "",
      "author": ""
    }
  ],
  "total_sub_events": 20,
  "scrape_time": "2025-09-11 19:24:45"
}