{
  "core_event_name": "澳大利亚加拿大军舰挑衅台海中线",
  "comments": [
    {
      "event_title": "加拿大与澳大利亚军舰过航台湾海峡，解放军硬核通告全球",
      "event_id": "event_1",
      "event_url": "http://haokan.baidu.com/v?pd=wisenatural&vid=11922554526774679843",
      "comment_index": 0,
      "user_id": "",
      "comment_time": "",
      "comment_content": "非百家号页面，跳过评论爬取",
      "user_location": "",
      "like_count": 0,
      "scrape_time": "2025-09-12 11:02:30",
      "event_time": "9月10日 01:28"
    },
    {
      "event_title": "九三阅兵刚结束,台海危险一幕!澳大利亚和加拿大军舰上门挑衅",
      "event_id": "event_2",
      "event_url": "http://haokan.baidu.com/v?pd=wisenatural&vid=14877120108552555226",
      "comment_index": 0,
      "user_id": "",
      "comment_time": "",
      "comment_content": "非百家号页面，跳过评论爬取",
      "user_location": "",
      "like_count": 0,
      "scrape_time": "2025-09-12 11:02:32",
      "event_time": "9月9日 15:39"
    },
    {
      "event_title": "澳加军舰强闯台海中线挑衅，赖清德幻想破灭",
      "event_id": "event_3",
      "event_url": "http://new.qq.com/rain/a/20250908A07RUP00",
      "comment_index": 0,
      "user_id": "",
      "comment_time": "",
      "comment_content": "非百家号页面，跳过评论爬取",
      "user_location": "",
      "like_count": 0,
      "scrape_time": "2025-09-12 11:02:34",
      "event_time": "9月8日 19:35"
    }
  ],
  "total_comments": 3,
  "scrape_time": "2025-09-12 11:02:34"
}