{
  "core_event_name": "足协选帅事件",
  "comments": [
    {
      "event_title": "国足选帅“外教优先”：是破局良药还是饮鸩止渴？",
      "event_id": "event_1",
      "event_url": "http://mbd.baidu.com/newspage/data/dtlandingwise?sourceFrom=reyi&nid=dt_5357743369383594709",
      "comment_index": 0,
      "user_id": "",
      "comment_time": "",
      "comment_content": "非百家号页面，跳过评论爬取",
      "user_location": "",
      "like_count": 0,
      "scrape_time": "2025-09-13 02:30:36",
      "event_time": "9月6日 07:40"
    },
    {
      "event_title": "足协选帅七条硬杠杠曝光，穆里尼奥意外成热门",
      "event_id": "event_2",
      "event_url": "http://baijiahao.baidu.com/s?id=1842435574388369626&wfr=spider&for=pc",
      "comment_index": 0,
      "user_id": "",
      "comment_time": "",
      "comment_content": "无评论",
      "user_location": "",
      "like_count": 0,
      "scrape_time": "2025-09-13 02:30:52",
      "event_time": "9月5日 22:44"
    },
    {
      "event_title": "国足公开选帅，目标打进2030世界杯",
      "event_id": "event_3",
      "event_url": "http://baijiahao.baidu.com/s?id=1842433972155987792&wfr=spider&for=pc",
      "comment_index": 1,
      "user_id": "百度网友7e5457c",
      "comment_time": "09-08 11:54",
      "comment_content": "又不要教练上场踢球，老是换教练能快速解决问题吗，换踢球的＇从全国范围选拔",
      "user_location": "广西",
      "like_count": 0,
      "scrape_time": "2025-09-13 02:31:08",
      "event_time": "9月5日 18:26"
    },
    {
      "event_title": "足协公开选聘国足主教练",
      "event_id": "event_4",
      "event_url": "http://baijiahao.baidu.com/s?id=1842408279691857755&wfr=spider&for=pc",
      "comment_index": 1,
      "user_id": "水水瓶",
      "comment_time": "09-05 18:55",
      "comment_content": "愿国足走的更远",
      "user_location": "陕西",
      "like_count": 0,
      "scrape_time": "2025-09-13 02:31:24"
    },
    {
      "event_title": "足协公开选聘国足主教练",
      "event_id": "event_4",
      "event_url": "http://baijiahao.baidu.com/s?id=1842408279691857755&wfr=spider&for=pc",
      "comment_index": 2,
      "user_id": "weixiaofei20",
      "comment_time": "09-05 19:19",
      "comment_content": "永远不知道要什么样的教练",
      "user_location": "美国",
      "like_count": 0,
      "scrape_time": "2025-09-13 02:31:24"
    },
    {
      "event_title": "足协公开选聘国足主教练",
      "event_id": "event_4",
      "event_url": "http://baijiahao.baidu.com/s?id=1842408279691857755&wfr=spider&for=pc",
      "comment_index": 3,
      "user_id": "杭修93",
      "comment_time": "09-05 20:55",
      "comment_content": "教练相对好选，球员选择难上难，哪来好球员？原国足球员技糙还屌，毫无斗志的到大有人在，换血都无从下手，能打能冲技高一筹的球员选择在中国如同大海捞针，国足新帅难有大的作为，到头又是一个死循环！",
      "user_location": "湖北",
      "like_count": 0,
      "scrape_time": "2025-09-13 02:31:24"
    },
    {
      "event_title": "足协公开选聘国足主教练",
      "event_id": "event_4",
      "event_url": "http://baijiahao.baidu.com/s?id=1842408279691857755&wfr=spider&for=pc",
      "comment_index": 4,
      "user_id": "我的名字叫做酷",
      "comment_time": "09-05 15:35",
      "comment_content": "足协这次要求变实在了，期待新掌舵人带队踢出新气象！",
      "user_location": "云南",
      "like_count": 1,
      "scrape_time": "2025-09-13 02:31:24"
    }
  ],
  "total_comments": 7,
  "scrape_time": "2025-09-13 02:31:24"
}