{
  "core_info": {
    "core_event_name": "抗日战争暨反法西斯战争胜利80周年",
    "update_time": "更新至2025年9月5日 07:53",
    "sub_event_count": 164,
    "scrape_time": "2025-09-10 12:54:07"
  },
  "sub_events": [
    {
      "id": "event_6",
      "title": "金正恩乘专列离京返程",
      "link": "https://mbd.baidu.com/newspage/data/dtlandingsuper?nid=dt_5286341969287675595&sourceFrom=search_a",
      "time": "9月5日 07:53",
      "summary": "【#金正恩乘专列离京返程#】#金正恩返程#据朝中社报道，朝鲜劳动党总书记、国务委员长金正恩结束对中国的访问日程，９月４日晚乘专列离开北京。",
      "author": "中国新闻网"
    },
    {
      "id": "event_7",
      "title": "抗战胜利80周年阅兵受阅部队开始回撤",
      "link": "https://baijiahao.baidu.com/s?id=1842329573015822379",
      "time": "9月4日 18:39",
      "summary": "",
      "author": ""
    },
    {
      "id": "event_8",
      "title": "美防长谈九三阅兵：美国不寻求和中国发生冲突",
      "link": "https://baijiahao.baidu.com/s?id=1842314179655239976&wfr=spider&for=pc",
      "time": "9月4日 14:34",
      "summary": "",
      "author": ""
    },
    {
      "id": "event_9",
      "title": "俄罗斯总统普京乘机回国",
      "link": "https://mbd.baidu.com/newspage/data/videolanding?nid=sv_15694237147215533677",
      "time": "9月4日 10:33",
      "summary": "",
      "author": ""
    },
    {
      "id": "event_10",
      "title": "特朗普：已观看九三阅兵，令人印象深刻",
      "link": "https://mbd.baidu.com/newspage/data/videolanding?nid=sv_11083689302196204111",
      "time": "9月4日 09:23",
      "summary": "",
      "author": ""
    },
    {
      "id": "event_11",
      "title": "韩媒：韩国会议长禹元植在北京与金正恩碰面并简短对话",
      "link": "https://baijiahao.baidu.com/s?id=1842245447210484537&wfr=spider&for=pc",
      "time": "9月3日 20:18",
      "summary": "",
      "author": ""
    },
    {
      "id": "event_12",
      "title": "普京邀请金正恩访俄，临别之际，两人握手、拥抱、互送祝福",
      "link": "https://baijiahao.baidu.com/s?id=1842243886149540924&wfr=spider&for=pc",
      "time": "9月3日 19:57",
      "summary": "",
      "author": ""
    },
    {
      "id": "event_13",
      "title": "特朗普谈中国阅兵：愿中国人民度过一个美好的庆祝日",
      "link": "https://mbd.baidu.com/newspage/data/landingsuper?context=%7B%22nid%22%3A%22news_8320221833883839614%22%7D",
      "time": "9月3日 16:24",
      "summary": "",
      "author": ""
    },
    {
      "id": "event_14",
      "title": "普京：中国举行的纪念活动“很精彩”",
      "link": "https://baijiahao.baidu.com/s?id=1842230189368257186&wfr=spider&for=pc",
      "time": "9月3日 16:17",
      "summary": "",
      "author": ""
    },
    {
      "id": "event_15",
      "title": "纪念中国人民抗日战争暨世界反法西斯战争胜利80周年大会结束",
      "link": "https://mbd.baidu.com/newspage/data/videolanding?nid=sv_3154618266215407651&sourceFrom=share",
      "time": "9月3日 12:19",
      "summary": "",
      "author": ""
    },
    {
      "id": "event_16",
      "title": "歌唱祖国！8万羽和平鸽展翅高飞，8万只气球腾空而起",
      "link": "https://mbd.baidu.com/newspage/data/videolanding?nid=sv_12820463113211915526&sourceFrom=share",
      "time": "9月3日 11:27",
      "summary": "",
      "author": ""
    },
    {
      "id": "event_17",
      "title": "“东风-5C”液体洲际战略核导弹亮相 打击范围覆盖全球",
      "link": "https://mbd.baidu.com/newspage/data/videolanding?nid=sv_16280585464395785976&sourceFrom=share",
      "time": "9月3日 10:38",
      "summary": "",
      "author": ""
    },
    {
      "id": "event_18",
      "title": "歼-16D、歼-20、歼-35A、歼-20S、歼-20A亮相",
      "link": "https://mbd.baidu.com/newspage/data/videolanding?nid=sv_5549770497897651217&sourceFrom=share",
      "time": "9月3日 10:32",
      "summary": "",
      "author": ""
    },
    {
      "id": "event_19",
      "title": "7架歼-10表演机划出14道彩烟",
      "link": "https://baijiahao.baidu.com/s?id=1842207854215587100&wfr=spider&for=pc",
      "time": "9月3日 10:24",
      "summary": "",
      "author": ""
    },
    {
      "id": "event_20",
      "title": "歼击机梯队：多型新型隐身战斗机集中亮相",
      "link": "https://baijiahao.baidu.com/s?id=1842207760943757175",
      "time": "9月3日 10:23",
      "summary": "",
      "author": ""
    },
    {
      "id": "event_21",
      "title": "核导弹第二方队：“东风-5C”液体洲际战略核导弹亮相",
      "link": "https://mbd.baidu.com/newspage/data/dtlandingsuper?nid=dt_4425058205801139784&sourceFrom=homepage",
      "time": "9月3日 10:22",
      "summary": "【核导弹第二方队：“东风-5C”液体洲际战略核导弹亮相】新华社北京9月3日电（记者梅世雄、王慧）东风浩荡，威震寰宇。核导弹第二方队3日上午通过天安门广场，光荣接受检阅。\n\n　　12台大型导弹运输车载着“东风-5C”液体洲际战略核导弹浩荡而来。核导弹第二方队是装备方队压轴出场的方队。\n\n　　“东风-5C”液体洲际战略核导弹是我国战略反击体系中的重要组成，打击范围覆盖全球，全时戒备、有效威慑，以武止戈、砥定乾坤。\n\n　　方队由火箭军某基地牵头抽组。",
      "author": "环球网"
    },
    {
      "id": "event_22",
      "title": "巨浪3潜射洲际导弹亮相",
      "link": "https://mbd.baidu.com/newspage/data/dtlandingsuper?nid=dt_5354041228122476317&sourceFrom=homepage",
      "time": "9月3日 10:19",
      "summary": "【#巨浪3受阅#】#巨浪3潜射洲际导弹#",
      "author": "环球网"
    },
    {
      "id": "event_23",
      "title": "核导弹第一方队震撼登场",
      "link": "https://baijiahao.baidu.com/s?id=1842207288308101440",
      "time": "9月3日 10:15",
      "summary": "",
      "author": ""
    },
    {
      "id": "event_24",
      "title": "鹰击-15、鹰击-19、鹰击-17、鹰击-20导弹亮相",
      "link": "https://mbd.baidu.com/newspage/data/videolanding?nid=sv_8304110634083492575&sourceFrom=share",
      "time": "9月3日 10:11",
      "summary": "",
      "author": ""
    },
    {
      "id": "event_25",
      "title": "战旗方队浩荡而来！感受80面战旗出场带来的压迫感",
      "link": "https://mbd.baidu.com/newspage/data/videolanding?nid=sv_5242035566576535038&sourceFrom=share",
      "time": "9月3日 10:07",
      "summary": "",
      "author": ""
    },
    {
      "id": "event_26",
      "title": "陆上猛虎海上蛟龙！两栖突击方队亮相阅兵场",
      "link": "https://mbd.baidu.com/newspage/data/videolanding?nid=sv_4075427740242927299&sourceFrom=share",
      "time": "9月3日 10:06",
      "summary": "",
      "author": ""
    },
    {
      "id": "event_27",
      "title": "英姿飒爽气势拉满！女民兵方队踏正步亮相阅兵现场",
      "link": "https://mbd.baidu.com/newspage/data/videolanding?nid=sv_10141143727679186836&sourceFrom=share",
      "time": "9月3日 10:00",
      "summary": "",
      "author": ""
    },
    {
      "id": "event_28",
      "title": "三支兵种首次亮相天安门广场",
      "link": "https://baijiahao.baidu.com/s?id=1842205809362886651",
      "time": "9月3日 09:52",
      "summary": "",
      "author": ""
    },
    {
      "id": "event_29",
      "title": "仪仗方队率先接受习近平检阅 “中国排面”威武亮相",
      "link": "https://baijiahao.baidu.com/s?id=1842205622231110906",
      "time": "9月3日 09:49",
      "summary": "",
      "author": ""
    },
    {
      "id": "event_30",
      "title": "阅兵式完整视频丨习近平乘车检阅地面方队 受阅方队发出豪迈誓言",
      "link": "https://baijiahao.baidu.com/s?id=1842205315304021774",
      "time": "9月3日 09:48",
      "summary": "",
      "author": ""
    },
    {
      "id": "event_31",
      "title": "韩胜延担任阅兵总指挥",
      "link": "https://baijiahao.baidu.com/s?id=1842205560421119755",
      "time": "9月3日 09:47",
      "summary": "",
      "author": ""
    },
    {
      "id": "event_32",
      "title": "歼20S震撼亮相",
      "link": "https://mbd.baidu.com/newspage/data/dtlandingsuper?nid=dt_4470967312773014585&sourceFrom=homepage",
      "time": "9月3日 09:47",
      "summary": "【#歼20S震撼亮相#】",
      "author": "环球网"
    },
    {
      "id": "event_33",
      "title": "DF61导弹亮相阅兵场",
      "link": "https://baijiahao.baidu.com/s?id=1842205080625047246",
      "time": "9月3日 09:41",
      "summary": "",
      "author": ""
    },
    {
      "id": "event_34",
      "title": "人民军队光荣接受习近平检阅",
      "link": "https://mbd.baidu.com/newspage/data/videolanding?nid=sv_11738810769683418197&sourceFrom=share",
      "time": "9月3日 09:30",
      "summary": "",
      "author": ""
    },
    {
      "id": "event_35",
      "title": "习近平乘车依次检阅徒步方队和装备方队",
      "link": "https://baijiahao.baidu.com/s?id=1842203993333822001",
      "time": "9月3日 09:23",
      "summary": "",
      "author": ""
    },
    {
      "id": "event_36",
      "title": "习近平以注目礼向党旗、国旗、军旗庄严致敬",
      "link": "https://baijiahao.baidu.com/s?id=1842203927026612305",
      "time": "9月3日 09:22",
      "summary": "",
      "author": ""
    },
    {
      "id": "event_37",
      "title": "阅兵总指挥报告受阅部队列队完毕，习近平下达检阅开始的命令",
      "link": "https://baijiahao.baidu.com/s?id=1842203858468672822",
      "time": "9月3日 09:20",
      "summary": "",
      "author": ""
    },
    {
      "id": "event_38",
      "title": "习近平：铭记历史、缅怀先烈、珍爱和平、开创未来",
      "link": "https://baijiahao.baidu.com/s?id=1842203233852798987",
      "time": "9月3日 09:11",
      "summary": "",
      "author": ""
    },
    {
      "id": "event_39",
      "title": "纪念中国人民抗日战争暨世界反法西斯战争胜利80周年大会开始",
      "link": "https://baijiahao.baidu.com/s?id=1842202546023078202",
      "time": "9月3日 09:00",
      "summary": "",
      "author": ""
    },
    {
      "id": "event_40",
      "title": "致敬英雄！习近平与天安门城楼观礼席的抗战老兵亲切握手",
      "link": "https://baijiahao.baidu.com/s?id=1842201848372960443",
      "time": "9月3日 08:49",
      "summary": "",
      "author": ""
    },
    {
      "id": "event_41",
      "title": "现场画面：俄罗斯总统普京抵达纪念大会现场",
      "link": "https://mbd.baidu.com/newspage/data/videolanding?nid=sv_4587045066068555301&sourceFrom=share",
      "time": "9月3日 08:34",
      "summary": "",
      "author": ""
    },
    {
      "id": "event_42",
      "title": "现场画面：金正恩抵达",
      "link": "https://mbd.baidu.com/newspage/data/videolanding?nid=sv_4056380016162040086&sourceFrom=share",
      "time": "9月3日 08:29",
      "summary": "",
      "author": ""
    },
    {
      "id": "event_43",
      "title": "现场：参加纪念大会的外方嘉宾陆续抵达",
      "link": "https://mbd.baidu.com/newspage/data/videolanding?nid=sv_7090899479976743146&sourceFrom=share",
      "time": "9月3日 08:08",
      "summary": "",
      "author": ""
    },
    {
      "id": "event_44",
      "title": "特种机 歼击机准备完毕 等待接受检阅",
      "link": "https://haokan.baidu.com/v?vid=6155112839566831916&collection_id=",
      "time": "9月3日 07:43",
      "summary": "",
      "author": ""
    },
    {
      "id": "event_45",
      "title": "天安门广场最新俯拍：徒步方队在长安街举旗行进",
      "link": "https://haokan.baidu.com/v?vid=4263227625483163532&pd=bjh&fr=bjhauthor&type=video",
      "time": "9月3日 07:20",
      "summary": "",
      "author": ""
    },
    {
      "id": "event_46",
      "title": "现场：嘉宾陆续在天安门城楼西侧观礼台就座",
      "link": "https://mbd.baidu.com/newspage/data/videolanding?nid=sv_15084406795398419741&sourceFrom=share",
      "time": "9月3日 07:13",
      "summary": "",
      "author": ""
    },
    {
      "id": "event_47",
      "title": "阅兵现场，受阅部队亮相！",
      "link": "https://mbd.baidu.com/newspage/data/videolanding?nid=sv_4029287744585050802&sourceFrom=share",
      "time": "9月3日 06:56",
      "summary": "",
      "author": ""
    },
    {
      "id": "event_48",
      "title": "印尼总统凌晨抵京 中方表示欢迎",
      "link": "https://baijiahao.baidu.com/s?id=1842192414141875486",
      "time": "9月3日 06:19",
      "summary": "",
      "author": ""
    },
    {
      "id": "event_49",
      "title": "朝鲜劳动党总书记、国务委员长金正恩抵达北京",
      "link": "https://baijiahao.baidu.com/s?id=1842157248186858048",
      "time": "9月2日 21:00",
      "summary": "",
      "author": ""
    },
    {
      "id": "event_50",
      "title": "韩国国会议长禹元植抵京",
      "link": "https://baijiahao.baidu.com/s?id=1842148755927979493",
      "time": "9月2日 18:45",
      "summary": "",
      "author": ""
    },
    {
      "id": "event_51",
      "title": "阿塞拜疆总统阿利耶夫抵达北京",
      "link": "https://baijiahao.baidu.com/s?id=1842138373003879593",
      "time": "9月2日 16:00",
      "summary": "",
      "author": ""
    },
    {
      "id": "event_52",
      "title": "是否有外国军队参加阅兵？外交部回应",
      "link": "https://baijiahao.baidu.com/s?id=1842137706017453073",
      "time": "9月2日 15:49",
      "summary": "",
      "author": ""
    },
    {
      "id": "event_53",
      "title": "土库曼斯坦总统别尔德穆哈梅多夫抵达北京",
      "link": "https://baijiahao.baidu.com/s?id=1842127460520078900",
      "time": "9月2日 13:07",
      "summary": "",
      "author": ""
    },
    {
      "id": "event_54",
      "title": "印度尼西亚外长苏吉约诺抵达北京",
      "link": "https://baijiahao.baidu.com/s?id=1842127401220513916",
      "time": "9月2日 13:06",
      "summary": "",
      "author": ""
    },
    {
      "id": "event_55",
      "title": "吉尔吉斯斯坦总统扎帕罗夫抵达北京",
      "link": "https://baijiahao.baidu.com/s?id=1842127399442788478",
      "time": "9月2日 13:06",
      "summary": "",
      "author": ""
    },
    {
      "id": "event_56",
      "title": "天安门广场核心区最新航拍：观礼台整体呈3个“人”字",
      "link": "https://mbd.baidu.com/newspage/data/videolanding?nid=sv_4728966891650943108&sourceFrom=qmj",
      "time": "9月2日 12:17",
      "summary": "",
      "author": ""
    },
    {
      "id": "event_57",
      "title": "致敬！112位抗战老兵获颁抗战胜利80周年纪念章",
      "link": "https://baijiahao.baidu.com/s?id=1842123706329123570&wfr=spider&for=pc",
      "time": "9月2日 12:07",
      "summary": "",
      "author": ""
    },
    {
      "id": "event_58",
      "title": "缅甸代总统敏昂莱抵达北京 将出席抗战胜利80周年纪念活动",
      "link": "https://baijiahao.baidu.com/s?id=1842120905933046141&wfr=spider&for=pc",
      "time": "9月2日 11:18",
      "summary": "",
      "author": ""
    },
    {
      "id": "event_59",
      "title": "法国小伙马库斯将参加人生第一次阅兵仪式",
      "link": "https://mbd.baidu.com/newspage/data/videolanding?nid=sv_8277011522536593323&sourceFrom=share",
      "time": "9月2日 11:08",
      "summary": "",
      "author": ""
    },
    {
      "id": "event_60",
      "title": "洪秀柱将出席九三阅兵：抗战胜利是全民族记忆，勿忘国耻唤起国魂",
      "link": "https://baijiahao.baidu.com/s?id=1842117196520881535&wfr=spider&for=pc",
      "time": "9月2日 10:24",
      "summary": "",
      "author": ""
    },
    {
      "id": "event_61",
      "title": "塞尔维亚总统武契奇抵京",
      "link": "https://baijiahao.baidu.com/s?id=1842111191902546352",
      "time": "9月2日 08:48",
      "summary": "",
      "author": ""
    },
    {
      "id": "event_62",
      "title": "俄媒记者发布普京车队凌晨经过北京天安门广场的画面",
      "link": "https://baijiahao.baidu.com/s?id=1842110986161300220",
      "time": "9月2日 08:45",
      "summary": "",
      "author": ""
    },
    {
      "id": "event_63",
      "title": "直升机空中护旗梯队率先通过广场",
      "link": "https://mbd.baidu.com/newspage/data/videolanding?nid=sv_2702203781231855342&sourceFrom=share",
      "time": "9月2日 08:38",
      "summary": "",
      "author": ""
    },
    {
      "id": "event_64",
      "title": "阅兵用时约70分钟，分两个步骤进行",
      "link": "https://mbd.baidu.com/newspage/data/videolanding?nid=sv_12298472436437998383&sourceFrom=share",
      "time": "9月2日 08:33",
      "summary": "",
      "author": ""
    },
    {
      "id": "event_65",
      "title": "天安门广场年号台整体亮相",
      "link": "https://baijiahao.baidu.com/s?id=1842109109459978674",
      "time": "9月2日 08:15",
      "summary": "",
      "author": ""
    },
    {
      "id": "event_66",
      "title": "斯洛伐克总理菲佐抵京 出席抗战胜利80周年纪念活动",
      "link": "https://baijiahao.baidu.com/s?id=1842105193348341854&wfr=spider&for=pc",
      "time": "9月2日 07:13",
      "summary": "",
      "author": ""
    },
    {
      "id": "event_67",
      "title": "哈萨克斯坦总统托卡耶夫抵达北京",
      "link": "https://baijiahao.baidu.com/s?id=1842077065930367491",
      "time": "9月1日 23:46",
      "summary": "",
      "author": ""
    },
    {
      "id": "event_68",
      "title": "塔吉克斯坦总统拉赫蒙抵达北京",
      "link": "https://baijiahao.baidu.com/s?id=1842077004881641397",
      "time": "9月1日 23:45",
      "summary": "",
      "author": ""
    },
    {
      "id": "event_69",
      "title": "马尔代夫总统穆伊兹抵达北京",
      "link": "https://baijiahao.baidu.com/s?id=1842072599023062419",
      "time": "9月1日 22:35",
      "summary": "",
      "author": ""
    },
    {
      "id": "event_70",
      "title": "乌兹别克斯坦总统米尔济约耶夫抵达北京",
      "link": "https://baijiahao.baidu.com/s?id=1842072539912756435",
      "time": "9月1日 22:34",
      "summary": "",
      "author": ""
    },
    {
      "id": "event_71",
      "title": "蒙古国总统呼日勒苏赫抵达北京",
      "link": "https://baijiahao.baidu.com/s?id=1842072538080158806",
      "time": "9月1日 22:34",
      "summary": "",
      "author": ""
    },
    {
      "id": "event_72",
      "title": "巴基斯坦总理夏巴兹抵达北京",
      "link": "https://baijiahao.baidu.com/s?id=1842072536202745056",
      "time": "9月1日 22:34",
      "summary": "",
      "author": ""
    },
    {
      "id": "event_73",
      "title": "多国领导人乘高铁抵达北京",
      "link": "https://baijiahao.baidu.com/s?id=1842069822046418160",
      "time": "9月1日 21:49",
      "summary": "",
      "author": ""
    },
    {
      "id": "event_74",
      "title": "纪念抗战胜利80周年大会和文艺晚会将于9月3日在京举行",
      "link": "https://baijiahao.baidu.com/s?id=1842062902205813571",
      "time": "9月1日 20:00",
      "summary": "",
      "author": ""
    },
    {
      "id": "event_75",
      "title": "金正恩已启程来华 将于2日抵达北京",
      "link": "https://mbd.baidu.com/newspage/data/videolanding?nid=sv_18238830221074467044&sourceFrom=share",
      "time": "9月1日 19:07",
      "summary": "",
      "author": ""
    },
    {
      "id": "event_76",
      "title": "李家超将率团出席抗战胜利80周年纪念活动",
      "link": "https://mbd.baidu.com/newspage/data/videolanding?nid=sv_4998449334812460473",
      "time": "9月1日 15:31",
      "summary": "",
      "author": ""
    },
    {
      "id": "event_77",
      "title": "俄罗斯、朝鲜军队会参加九三阅兵吗？外交部回应",
      "link": "https://baijiahao.baidu.com/s?id=1842045534011149668",
      "time": "9月1日 15:23",
      "summary": "",
      "author": ""
    },
    {
      "id": "event_78",
      "title": "抗战胜利80周年 迎接纪念大会 天安门广场布置即将完成",
      "link": "https://mbd.baidu.com/newspage/data/videolanding?nid=sv_11883358572698115523&sourceFrom=share",
      "time": "9月1日 15:09",
      "summary": "",
      "author": ""
    },
    {
      "id": "event_79",
      "title": "九三阅兵 具体安排来了",
      "link": "https://baijiahao.baidu.com/s?id=1842043243664580342",
      "time": "9月1日 15:01",
      "summary": "",
      "author": ""
    },
    {
      "id": "event_80",
      "title": "华侨华人在世界各地举行的纪念活动及其对抗战的贡献",
      "link": "https://baijiahao.baidu.com/s?id=1842043993941109703",
      "time": "9月1日 15:00",
      "summary": "",
      "author": ""
    },
    {
      "id": "event_81",
      "title": "抗战胜利80周年纪念活动总体安排公布",
      "link": "https://baijiahao.baidu.com/s?id=1842039845101181409",
      "time": "9月1日 13:56",
      "summary": "",
      "author": ""
    },
    {
      "id": "event_82",
      "title": "津巴布韦总统姆南加古瓦抵京 将出席抗战胜利80周年纪念活动",
      "link": "https://baijiahao.baidu.com/s?id=1842032236357811869",
      "time": "9月1日 11:53",
      "summary": "",
      "author": ""
    },
    {
      "id": "event_83",
      "title": "香港侨界举办纪念抗战胜利80周年大会",
      "link": "https://baijiahao.baidu.com/s?id=1841984602398117773&wfr=spider&for=pc",
      "time": "8月31日 23:16",
      "summary": "",
      "author": ""
    },
    {
      "id": "event_84",
      "title": "第三场记者招待会，特别提到“王二小”等抗战英雄事迹",
      "link": "https://baijiahao.baidu.com/s?id=1841943084435093552",
      "time": "8月31日 12:16",
      "summary": "",
      "author": ""
    },
    {
      "id": "event_85",
      "title": "我国抗战纪念馆体系基本形成",
      "link": "https://baijiahao.baidu.com/s?id=1841936222964392610",
      "time": "8月31日 10:27",
      "summary": "",
      "author": ""
    },
    {
      "id": "event_86",
      "title": "全国有抗战主题不可移动文物1万余处、可移动文物16万余件/套",
      "link": "https://baijiahao.baidu.com/s?id=1841936105497619359",
      "time": "8月31日 10:25",
      "summary": "",
      "author": ""
    },
    {
      "id": "event_87",
      "title": "全国年均举办抗战展500余个，逾6000万人次参观遗址场馆",
      "link": "https://baijiahao.baidu.com/s?id=1841935909933856509",
      "time": "8月31日 10:22",
      "summary": "",
      "author": ""
    },
    {
      "id": "event_88",
      "title": "我国先后公布四批国家级抗战纪念设施",
      "link": "https://baijiahao.baidu.com/s?id=1841935848812582548",
      "time": "8月31日 10:21",
      "summary": "",
      "author": ""
    },
    {
      "id": "event_89",
      "title": "退役军人事务部：推动7.7万余座零散烈士墓迁至烈士陵园",
      "link": "https://baijiahao.baidu.com/s?id=1841935478097156000",
      "time": "8月31日 10:15",
      "summary": "",
      "author": ""
    },
    {
      "id": "event_90",
      "title": "中国驻黎巴嫩大使馆举办纪念抗战胜利80周年座谈会",
      "link": "https://baijiahao.baidu.com/s?id=1841892967768714243",
      "time": "8月30日 22:59",
      "summary": "",
      "author": ""
    },
    {
      "id": "event_91",
      "title": "香港特区政府举行典礼纪念抗战胜利80周年",
      "link": "https://baijiahao.baidu.com/s?id=1841856129910479433&wfr=spider&for=pc",
      "time": "8月30日 13:12",
      "summary": "",
      "author": ""
    },
    {
      "id": "event_92",
      "title": "国台办：台湾各界代表人士来京参加抗战胜利纪念活动，堂堂正正",
      "link": "https://baijiahao.baidu.com/s?id=1841800860659792032",
      "time": "8月29日 22:35",
      "summary": "",
      "author": ""
    },
    {
      "id": "event_93",
      "title": "首次集中展示！4支战略兵种方队将擎崭新军旗亮相九三阅兵",
      "link": "http://baijiahao.baidu.com/s?id=1841780829179483541",
      "time": "8月29日 17:32",
      "summary": "",
      "author": ""
    },
    {
      "id": "event_94",
      "title": "战略兵种受阅方队 擎崭新军旗集中亮相",
      "link": "https://mbd.baidu.com/newspage/data/videolanding?nid=sv_13327541052199186533",
      "time": "8月29日 16:48",
      "summary": "",
      "author": ""
    },
    {
      "id": "event_95",
      "title": "汇总｜事关九三阅兵 第二场记者招待会聚焦这些问题",
      "link": "http://baijiahao.baidu.com/s?id=1841762577983806854",
      "time": "8月29日 12:27",
      "summary": "",
      "author": ""
    },
    {
      "id": "event_96",
      "title": "空军第九批女飞行员将参加九三阅兵",
      "link": "https://baijiahao.baidu.com/s?id=1841749183127190447",
      "time": "8月29日 08:56",
      "summary": "",
      "author": ""
    },
    {
      "id": "event_97",
      "title": "天安门广场核心区布置基本就绪 阅兵当天广场可容纳超5万人观礼",
      "link": "https://baijiahao.baidu.com/s?id=1841744334589639727",
      "time": "8月29日 07:40",
      "summary": "",
      "author": ""
    },
    {
      "id": "event_98",
      "title": "北京警方提示：近期两个净空限制区《通告》有区别",
      "link": "https://baijiahao.baidu.com/s?id=1841686894057431903",
      "time": "8月28日 16:24",
      "summary": "",
      "author": ""
    },
    {
      "id": "event_99",
      "title": "抗战胜利80周年纪念邮票将于9月3日发行",
      "link": "https://baijiahao.baidu.com/s?id=1841685889526756996",
      "time": "8月28日 16:08",
      "summary": "",
      "author": ""
    },
    {
      "id": "event_100",
      "title": "参加九三阅兵外方嘉宾名单未提西方主要国家 中方回应",
      "link": "https://baijiahao.baidu.com/s?id=1841685758528510194&wfr=spider&for=pc",
      "time": "8月28日 16:05",
      "summary": "",
      "author": ""
    },
    {
      "id": "event_101",
      "title": "外交部回应金正恩将出席纪念活动",
      "link": "https://baijiahao.baidu.com/s?id=1841669810503660621",
      "time": "8月28日 11:52",
      "summary": "",
      "author": ""
    },
    {
      "id": "event_102",
      "title": "阅兵准备基本就绪，已经进入倒计时",
      "link": "https://baijiahao.baidu.com/s?id=1841665279066113894",
      "time": "8月28日 10:41",
      "summary": "",
      "author": ""
    },
    {
      "id": "event_103",
      "title": "长安街沿线布置10组立体花坛",
      "link": "https://baijiahao.baidu.com/s?id=1841664239967548106",
      "time": "8月28日 10:23",
      "summary": "",
      "author": ""
    },
    {
      "id": "event_104",
      "title": "天安门广场布置年号台等要素  群众可到临时观礼台现场看阅兵",
      "link": "https://baijiahao.baidu.com/s?id=1841664052065129571",
      "time": "8月28日 10:21",
      "summary": "",
      "author": ""
    },
    {
      "id": "event_105",
      "title": "9月3日晚人民大会堂举办抗战胜利80周年文艺晚会",
      "link": "https://baijiahao.baidu.com/s?id=1841663705492808274",
      "time": "8月28日 10:14",
      "summary": "",
      "author": ""
    },
    {
      "id": "event_106",
      "title": "14国50位友人或遗属出席抗战纪念活动",
      "link": "https://baijiahao.baidu.com/s?id=1841663488622339688",
      "time": "8月28日 10:12",
      "summary": "",
      "author": ""
    },
    {
      "id": "event_107",
      "title": "金正恩、普京等26位外国元首和政府首脑将出席九三阅兵",
      "link": "https://baijiahao.baidu.com/s?id=1841663203594437617",
      "time": "8月28日 10:07",
      "summary": "",
      "author": ""
    },
    {
      "id": "event_108",
      "title": "28日10时举办九三阅兵首场记者招待会",
      "link": "https://baijiahao.baidu.com/s?id=1841649644325121043&wfr=spider&for=pc",
      "time": "8月28日 06:29",
      "summary": "",
      "author": ""
    },
    {
      "id": "event_109",
      "title": "中央广播电视总台召开纪念抗战胜利80周年宣传报道动员会",
      "link": "https://baijiahao.baidu.com/s?id=1841628635035365323",
      "time": "8月28日 01:00",
      "summary": "",
      "author": ""
    },
    {
      "id": "event_110",
      "title": "抢先看！60秒混剪盛大阅兵训练",
      "link": "https://mbd.baidu.com/newspage/data/videolanding?nid=sv_3842317072814214525",
      "time": "8月27日 16:35",
      "summary": "",
      "author": ""
    },
    {
      "id": "event_111",
      "title": "震撼！受阅官兵的回答让人泪目",
      "link": "https://mbd.baidu.com/newspage/data/videolanding?nid=sv_8172627843450197737&sourceFrom=share",
      "time": "8月27日 08:32",
      "summary": "",
      "author": ""
    },
    {
      "id": "event_112",
      "title": "长安街沿线花坛首次应用甘蔗高粱",
      "link": "https://baijiahao.baidu.com/s?id=1841518405084284013",
      "time": "8月26日 19:46",
      "summary": "",
      "author": ""
    },
    {
      "id": "event_113",
      "title": "九三阅兵三次演练卡点大片",
      "link": "https://mbd.baidu.com/newspage/data/videolanding?nid=sv_5187822151921702762",
      "time": "8月26日 17:00",
      "summary": "",
      "author": ""
    },
    {
      "id": "event_114",
      "title": "九三阅兵天安门广场布置亮相",
      "link": "https://baijiahao.baidu.com/s?id=1841337524781143808",
      "time": "8月24日 19:50",
      "summary": "",
      "author": ""
    },
    {
      "id": "event_115",
      "title": "抗战胜利80周年大会第三次演练完成",
      "link": "https://baijiahao.baidu.com/s?id=1841289145931544771",
      "time": "8月24日 07:02",
      "summary": "",
      "author": ""
    },
    {
      "id": "event_116",
      "title": "巴基斯坦总理夏巴兹：十分期待赴华出席抗战胜利80周年纪念活动",
      "link": "https://baijiahao.baidu.com/s?id=1841117691680562291&wfr=spider&for=pc",
      "time": "8月22日 09:37",
      "summary": "",
      "author": ""
    },
    {
      "id": "event_117",
      "title": "海外侨界开展多元活动纪念抗战胜利80周年",
      "link": "https://baijiahao.baidu.com/s?id=1841116632835671857&wfr=spider&for=pc",
      "time": "8月22日 09:09",
      "summary": "",
      "author": ""
    },
    {
      "id": "event_118",
      "title": "九三阅兵3名旗手揭晓：均为“90后”，平均身高189厘米",
      "link": "https://baijiahao.baidu.com/s?id=1841024347857258581&wfr=spider&for=pc",
      "time": "8月21日 08:53",
      "summary": "",
      "author": ""
    },
    {
      "id": "event_119",
      "title": "新一代武器装备将集中亮相九三阅兵",
      "link": "https://baijiahao.baidu.com/s?id=1841019271521551204&wfr=spider&for=pc",
      "time": "8月21日 07:24",
      "summary": "",
      "author": ""
    },
    {
      "id": "event_120",
      "title": "抗战胜利80周年阅兵准备工作进展顺利",
      "link": "https://baijiahao.baidu.com/s?id=1841018171562291053&wfr=spider&for=pc",
      "time": "8月21日 07:07",
      "summary": "",
      "author": ""
    },
    {
      "id": "event_121",
      "title": "阅兵训练高清大图抢先看",
      "link": "https://baijiahao.baidu.com/s?id=1840977734086271731",
      "time": "8月20日 20:33",
      "summary": "",
      "author": ""
    },
    {
      "id": "event_122",
      "title": "九三阅兵外国领导人出席情况，外交部：适时发布",
      "link": "https://baijiahao.baidu.com/s?id=1840958590936745261",
      "time": "8月20日 15:28",
      "summary": "",
      "author": ""
    },
    {
      "id": "event_123",
      "title": "九三阅兵详细安排来了！一图速览",
      "link": "https://baijiahao.baidu.com/s?id=1840952175857849106",
      "time": "8月20日 13:46",
      "summary": "",
      "author": ""
    },
    {
      "id": "event_124",
      "title": "这次阅兵训练坚持实战标准，依托战时指挥体制指挥阅兵行动",
      "link": "https://baijiahao.baidu.com/s?id=1840942171419294825",
      "time": "8月20日 11:07",
      "summary": "",
      "author": ""
    },
    {
      "id": "event_125",
      "title": "联合军乐团整体设置14个排面 前排设置80名礼号手",
      "link": "https://baijiahao.baidu.com/s?id=1840940977838680023",
      "time": "8月20日 10:48",
      "summary": "",
      "author": ""
    },
    {
      "id": "event_126",
      "title": "九三阅兵首次亮相的新型装备占比很大",
      "link": "https://mbd.baidu.com/newspage/data/videolanding?nid=sv_11476479404329606679&sourceFrom=share",
      "time": "8月20日 10:43",
      "summary": "",
      "author": ""
    },
    {
      "id": "event_127",
      "title": "国新办发布会介绍阅兵准备工作有关情况",
      "link": "https://mbd.baidu.com/newspage/data/videolanding?nid=sv_8204353780409098881&sourceFrom=share",
      "time": "8月20日 10:10",
      "summary": "",
      "author": ""
    },
    {
      "id": "event_128",
      "title": "国新办将举行新闻发布会 介绍阅兵准备工作有关情况",
      "link": "https://baijiahao.baidu.com/s?id=1840768210416978583&wfr=spider&for=pc",
      "time": "8月18日 13:02",
      "summary": "",
      "author": ""
    },
    {
      "id": "event_129",
      "title": "抗战胜利80周年大会第二次演练完成",
      "link": "https://baijiahao.baidu.com/s?id=1840654967505800123",
      "time": "8月17日 07:02",
      "summary": "",
      "author": ""
    },
    {
      "id": "event_130",
      "title": "古巴隆重举行纪念中国人民抗战胜利80周年大会",
      "link": "https://baijiahao.baidu.com/s?id=1840530048912878929&wfr=spider&for=pc",
      "time": "8月15日 21:51",
      "summary": "",
      "author": ""
    },
    {
      "id": "event_131",
      "title": "“日本投降了，我们胜利了！”",
      "link": "https://baijiahao.baidu.com/s?id=1840481163605183198",
      "time": "8月15日 08:58",
      "summary": "",
      "author": ""
    },
    {
      "id": "event_132",
      "title": "北京：纪念抗战胜利80周年主题花坛搭建中",
      "link": "https://baijiahao.baidu.com/s?id=1840421426750918085",
      "time": "8月14日 17:01",
      "summary": "",
      "author": ""
    },
    {
      "id": "event_133",
      "title": "纪念抗战胜利80周年大会首次演练结束",
      "link": "https://baijiahao.baidu.com/s?id=1840020629917927321",
      "time": "8月10日 07:00",
      "summary": "",
      "author": ""
    },
    {
      "id": "event_134",
      "title": "纪念抗战胜利80周年专题展在上海举行",
      "link": "https://baijiahao.baidu.com/s?id=1839965830426960191",
      "time": "8月9日 16:26",
      "summary": "",
      "author": ""
    },
    {
      "id": "event_135",
      "title": "纪念抗战胜利80周年图片展在阿根廷举办",
      "link": "https://baijiahao.baidu.com/s?id=1839760666738696254",
      "time": "8月7日 10:07",
      "summary": "",
      "author": ""
    },
    {
      "id": "event_136",
      "title": "纪念抗战胜利80周年名家名作展在港举办",
      "link": "https://baijiahao.baidu.com/s?id=1839693725671905585",
      "time": "8月6日 16:24",
      "summary": "",
      "author": ""
    },
    {
      "id": "event_137",
      "title": "塞尔维亚总统武契奇：将于9月访问中国",
      "link": "https://baijiahao.baidu.com/s?id=1839574909694001290&wfr=spider&for=pc",
      "time": "8月5日 08:55",
      "summary": "",
      "author": ""
    },
    {
      "id": "event_138",
      "title": "武契奇称将于9月访华并出席中国阅兵 或将与普京在中国会面",
      "link": "https://baijiahao.baidu.com/s?id=1839484282578280717&wfr=spider&for=pc",
      "time": "8月4日 08:52",
      "summary": "",
      "author": ""
    },
    {
      "id": "event_139",
      "title": "中方是否邀请特朗普访问中国？外交部回应",
      "link": "https://baijiahao.baidu.com/s?id=1838978233926188795&wfr=spider&for=pc",
      "time": "7月29日 18:51",
      "summary": "",
      "author": ""
    },
    {
      "id": "event_140",
      "title": "特朗普：期待不久的将来访问中国",
      "link": "https://baijiahao.baidu.com/s?id=1838401740688594832&wfr=spider&for=pc",
      "time": "7月23日 10:08",
      "summary": "",
      "author": ""
    },
    {
      "id": "event_141",
      "title": "7月16日零时起 北京9个区将被设置为净空限制区",
      "link": "https://baijiahao.baidu.com/s?id=1837695089000427862&wfr=spider&for=pc",
      "time": "7月15日 14:56",
      "summary": "",
      "author": ""
    },
    {
      "id": "event_142",
      "title": "欢迎境内外记者采访",
      "link": "https://baijiahao.baidu.com/s?id=1837584073044602381",
      "time": "7月14日 09:31",
      "summary": "",
      "author": ""
    },
    {
      "id": "event_143",
      "title": "主播说联播丨总书记参观百团大战纪念馆，传递哪些信息？",
      "link": "https://baijiahao.baidu.com/s?id=1837070847639834074",
      "time": "7月8日 17:31",
      "summary": "",
      "author": ""
    },
    {
      "id": "event_144",
      "title": "赵一曼从被捕到英勇就义的详细档案，将首次展出",
      "link": "https://baijiahao.baidu.com/s?id=1836617141711117536",
      "time": "7月3日 17:21",
      "summary": "",
      "author": ""
    },
    {
      "id": "event_145",
      "title": "重磅！纪念抗战胜利80周年一系列文艺活动发布",
      "link": "https://baijiahao.baidu.com/s?id=1836598234805528537",
      "time": "7月3日 12:22",
      "summary": "",
      "author": ""
    },
    {
      "id": "event_146",
      "title": "总台将推出一批抗战胜利80周年专题片纪录片和影视文艺作品",
      "link": "https://baijiahao.baidu.com/s?id=1836590246568650540",
      "time": "7月3日 10:29",
      "summary": "",
      "author": ""
    },
    {
      "id": "event_147",
      "title": "国新办发布会：纪念抗战胜利80周年主题展览7月7日开幕",
      "link": "https://baijiahao.baidu.com/s?id=1836591065246703777",
      "time": "7月3日 10:28",
      "summary": "",
      "author": ""
    },
    {
      "id": "event_148",
      "title": "8月至10月举办纪念抗战胜利80周年优秀舞台艺术作品展演",
      "link": "https://baijiahao.baidu.com/s?id=1836594870413992549&wfr=spider&for=pc",
      "time": "7月3日 10:20",
      "summary": "",
      "author": ""
    },
    {
      "id": "event_149",
      "title": "文艺晚会9月3日晚将在北京举行",
      "link": "https://baijiahao.baidu.com/s?id=1836589804233026398",
      "time": "7月3日 10:13",
      "summary": "",
      "author": ""
    },
    {
      "id": "event_150",
      "title": "国新办将举行新闻发布会介绍抗战胜利80周年主题展览等有关情况",
      "link": "https://baijiahao.baidu.com/s?id=1836421920698130768&wfr=spider&for=pc",
      "time": "7月1日 13:38",
      "summary": "",
      "author": ""
    },
    {
      "id": "event_151",
      "title": "澳门将举办系列活动纪念抗战胜利80周年",
      "link": "https://baijiahao.baidu.com/s?id=1835987585603870359",
      "time": "6月26日 18:36",
      "summary": "",
      "author": ""
    },
    {
      "id": "event_152",
      "title": "今年九三胜利日大阅兵，这种兵将首次亮相",
      "link": "https://mbd.baidu.com/newspage/data/dtlandingsuper?nid=dt_4605836084998199929&sourceFrom=homepage",
      "time": "6月26日 10:59",
      "summary": "【都有数｜今年九三胜利日大阅兵，这种兵将首次亮相——】#九三胜利日阅兵#（来源：北京日报客户端）都有数｜今年九三胜利日大阅兵，这种兵将首次亮相——",
      "author": "京报网"
    },
    {
      "id": "event_153",
      "title": "一图速览丨抗战胜利80周年纪念活动十项安排",
      "link": "https://baijiahao.baidu.com/s?id=1835786292996717278",
      "time": "6月24日 13:16",
      "summary": "",
      "author": ""
    },
    {
      "id": "event_154",
      "title": "这场发布会，信息量很大！",
      "link": "https://baijiahao.baidu.com/s?id=1835783082300118325",
      "time": "6月24日 12:23",
      "summary": "",
      "author": ""
    },
    {
      "id": "event_155",
      "title": "重磅！阅兵安排，来了！",
      "link": "https://baijiahao.baidu.com/s?id=1835780911787862053",
      "time": "6月24日 11:50",
      "summary": "",
      "author": ""
    },
    {
      "id": "event_156",
      "title": "阅兵将安排执行过维和任务的部队参阅",
      "link": "https://baijiahao.baidu.com/s?id=1835778524357488445",
      "time": "6月24日 11:44",
      "summary": "",
      "author": ""
    },
    {
      "id": "event_157",
      "title": "抗战胜利80周年阅兵主题公布",
      "link": "https://baijiahao.baidu.com/s?id=1835780031566290888",
      "time": "6月24日 11:37",
      "summary": "",
      "author": ""
    },
    {
      "id": "event_158",
      "title": "纪念活动将邀请有关国家领导人、前政要、高级别官员等出席",
      "link": "https://baijiahao.baidu.com/s?id=1835777979325398571",
      "time": "6月24日 11:30",
      "summary": "",
      "author": ""
    },
    {
      "id": "event_159",
      "title": "阅兵式参阅武器装备均为国产现役主战装备 三大特点解读",
      "link": "https://baijiahao.baidu.com/s?id=1835778977386640360",
      "time": "6月24日 11:23",
      "summary": "",
      "author": ""
    },
    {
      "id": "event_160",
      "title": "民兵将首次参加以纪念抗战胜利为主题的阅兵活动",
      "link": "https://baijiahao.baidu.com/s?id=1835778275630391093",
      "time": "6月24日 11:22",
      "summary": "",
      "author": ""
    },
    {
      "id": "event_161",
      "title": "阅兵将安排参加过抗战的老战士等代表到天安门现场观礼",
      "link": "https://baijiahao.baidu.com/s?id=1835776823403064115",
      "time": "6月24日 11:21",
      "summary": "",
      "author": ""
    },
    {
      "id": "event_162",
      "title": "习近平将出席纪念大会并发表重要讲话",
      "link": "https://baijiahao.baidu.com/s?id=1835774022428942535",
      "time": "6月24日 11:21",
      "summary": "",
      "author": ""
    },
    {
      "id": "event_163",
      "title": "阅兵由徒步方队装备方队和空中梯队组成",
      "link": "https://baijiahao.baidu.com/s?id=1835776320342659301&wfr=spider&for=pc",
      "time": "6月24日 10:38",
      "summary": "",
      "author": ""
    },
    {
      "id": "event_164",
      "title": "中国人民抗日战争胜利80周年纪念章将颁发",
      "link": "https://baijiahao.baidu.com/s?id=1835774588168698175",
      "time": "6月24日 10:10",
      "summary": "",
      "author": ""
    },
    {
      "id": "event_165",
      "title": "抗战胜利80周年纪念大会包括检阅部队9月3日上午举行",
      "link": "https://baijiahao.baidu.com/s?id=1835774022428942535",
      "time": "6月24日 10:02",
      "summary": "",
      "author": ""
    },
    {
      "id": "event_166",
      "title": "国新办发布会介绍抗战胜利80周年纪念活动总体安排",
      "link": "https://baijiahao.baidu.com/s?id=1835773927966716857",
      "time": "6月24日 10:00",
      "summary": "",
      "author": ""
    },
    {
      "id": "event_167",
      "title": "俄总统助理：普京8月31日至9月3日将访华停留4天",
      "link": "https://baijiahao.baidu.com/s?id=1835678863289666095&wfr=spider&for=pc",
      "time": "6月23日 08:42",
      "summary": "",
      "author": ""
    },
    {
      "id": "event_168",
      "title": "中国抗日战争暨世界反法西斯战争胜利80周年纪念活动标识发布",
      "link": "https://mbd.baidu.com/newspage/data/videolanding?nid=sv_15379293303987743021&sourceFrom=share",
      "time": "5月13日 09:11",
      "summary": "",
      "author": ""
    },
    {
      "id": "event_169",
      "title": "王毅：今年隆重纪念中国人民抗日战争胜利80周年",
      "link": "https://baijiahao.baidu.com/s?id=1825901978646381315&wfr=spider&for=pc",
      "time": "3月7日 10:50",
      "summary": "",
      "author": ""
    }
  ],
  "total_sub_events": 164,
  "scrape_time": "2025-09-10 12:54:48"
}