{
  "core_info": {
    "core_event_name": "羽毛球世锦赛国羽夺五金",
    "update_time": "更新至20250904",
    "sub_event_count": 0,
    "scrape_time": "2025-09-12 22:56:57"
  },
  "sub_events": [
    {
      "id": "event_1",
      "title": "羽毛球世锦赛落幕，国羽5项决赛夺2金",
      "link": "http://haokan.baidu.com/v?pd=wisenatural&vid=7118785460588852245",
      "time": "9月4日 16:48",
      "summary": "",
      "author": ""
    },
    {
      "id": "event_2",
      "title": "世锦赛决赛国羽全力冲击5金，专家预测或将斩获3金",
      "link": "http://haokan.baidu.com/v?pd=wisenatural&vid=6545587231144099142",
      "time": "9月3日 15:03",
      "summary": "",
      "author": ""
    },
    {
      "id": "event_3",
      "title": "国羽征战世锦赛表现亮眼",
      "link": "http://www.163.com/dy/article/K8H80QQ30550TYQ0.html",
      "time": "9月3日 09:39",
      "summary": "",
      "author": ""
    },
    {
      "id": "event_4",
      "title": "羽毛球世锦赛决赛，国羽力争五金，预测夺三冠",
      "link": "http://haokan.baidu.com/v?pd=wisenatural&vid=16130127077905035521",
      "time": "9月3日 09:01",
      "summary": "",
      "author": ""
    }
  ],
  "total_sub_events": 4,
  "scrape_time": "2025-09-12 22:57:11"
}