{
  "core_info": {
    "core_event_name": "蔚来第二季度业绩分析",
    "update_time": "更新至20250904",
    "sub_event_count": 0,
    "scrape_time": "2025-09-12 20:32:34"
  },
  "sub_events": [
    {
      "id": "event_1",
      "title": "蔚来2025年第二季度净亏损49.9亿元同比收窄1%",
      "link": "http://k.sina.cn/article_5952915720_162d2490806702eknw.html",
      "time": "9月4日 20:10",
      "summary": "",
      "author": ""
    },
    {
      "id": "event_2",
      "title": "蔚来汽车业绩喜忧参半，股价反弹缺乏动能",
      "link": "http://baijiahao.baidu.com/s?id=1842236889476363412&wfr=spider&for=pc",
      "time": "9月3日 17:16",
      "summary": "",
      "author": ""
    },
    {
      "id": "event_3",
      "title": "李斌:用户不买蔚来车 30%-40% 因担心倒闭,四季度盈利成关键",
      "link": "http://www.ithome.com/0/879/228.htm",
      "time": "8月30日 16:40",
      "summary": "",
      "author": ""
    }
  ],
  "total_sub_events": 3,
  "scrape_time": "2025-09-12 20:32:48"
}