{
  "core_info": {
    "core_event_name": "葡萄牙缆车出轨事故",
    "update_time": "更新至20250908",
    "sub_event_count": 0,
    "scrape_time": "2025-09-12 15:00:45"
  },
  "sub_events": [
    {
      "id": "event_1",
      "title": "葡萄牙缆车出轨事故",
      "link": "http://weibo.com/5016630485/Q3CRP3ZdM",
      "time": "9月8日 16:42",
      "summary": "",
      "author": ""
    },
    {
      "id": "event_2",
      "title": "葡萄牙旅游缆车脱轨已致15死18伤",
      "link": "http://weibo.com/2492219020/Q32Nfel4E",
      "time": "9月4日 20:52",
      "summary": "",
      "author": ""
    },
    {
      "id": "event_3",
      "title": "葡萄牙里斯本著名旅游缆车侧翻出轨 已致15人死亡",
      "link": "http://tv.cctv.com/2025/09/04/VIDE3vzSLmkNOoBHin2XWKQd250904.shtml",
      "time": "9月4日 16:30",
      "summary": "",
      "author": ""
    }
  ],
  "total_sub_events": 3,
  "scrape_time": "2025-09-12 15:01:00"
}